{
  "data": [
    {
      "coinName": "PontoonToken (TOON)",
      "address": "0xaeE433ADeBe0FBB88dAa47eF0C1A513CaA52EF02",
      "price": "$0.0297",
      "change": "250.63%",
      "isUp": true,
      "volume": "$59,141.00",
      "marketCap": "--",
      "holders": "1,999"
    },
    {
      "coinName": "HashBit Blockchain (HBIT)",
      "address": "0x142749adb4176ee465592bbaadd5bd71f58017f1",
      "price": "$0.000.",
      "change": "77.95%",
      "isUp": true,
      "volume": "$7.00",
      "marketCap": "--",
      "holders": "566"
    },
    {
      "coinName": "FinNexus (FNX)",
      "address": "0xdfd9e2a17596cad6295ecffda42d9b6f63f7b5d5",
      "price": "$0.0076",
      "change": "72.24%",
      "isUp": true,
      "volume": "$184,825.00",
      "marketCap": "$2,711,791.00",
      "holders": "1,670"
    },
    {
      "coinName": "Linear Token (LINA)",
      "address": "0x762539b45a1dcce3d36d080f74d1aed37844b878",
      "price": "$0.0329",
      "change": "50.76%",
      "isUp": true,
      "volume": "$3,330,877.00",
      "marketCap": "--",
      "holders": "20,926"
    },
    {
      "coinName": "GourmetGalaxy (GUM)",
      "address": "0xc53708664b99df348dd27c3ac0759d2da9c40462",
      "price": "$0.4441",
      "change": "42.55%",
      "isUp": true,
      "volume": "$650,399.00",
      "marketCap": "$1,470,820.00",
      "holders": "7,416"
    },
    {
      "coinName": "GoatGang (GGT)",
      "address": "0x0195Af07ff81E2dCdd40BB8F7719fb4426a978C9",
      "price": "$139.96",
      "change": "37.58%",
      "isUp": true,
      "volume": "$22,982,844.00",
      "marketCap": "--",
      "holders": "29"
    },
    {
      "coinName": "Raven Protocol (RAVEN)",
      "address": "0xcd7c5025753a49f1881b31c48caa7c517bb46308",
      "price": "$0.0016",
      "change": "34.20%",
      "isUp": true,
      "volume": "$143,372.00",
      "marketCap": "$7,086,817.00",
      "holders": "3,404"
    },
    {
      "coinName": "bZx Protocol Token (BZRX)",
      "address": "0x4b87642aedf10b642be4663db842ecc5a88bf5ba",
      "price": "$0.1090",
      "change": "31.81%",
      "isUp": true,
      "volume": "$11,267.00",
      "marketCap": "$56,663,258.00",
      "holders": "1,253"
    },
    {
      "coinName": "GAMMA (GAMMA)",
      "address": "0xb3cb6d2f8f2fde203a022201c81a96c167607f15",
      "price": "$0.0496",
      "change": "21.80%",
      "isUp": true,
      "volume": "$0.00",
      "marketCap": "--",
      "holders": "6,289"
    },
    {
      "coinName": "Binance-Peg Firo Token (FIRO)",
      "address": "0xd5d0322b6bab6a762c79f8c81a0b674778e13aed",
      "price": "$3.570.",
      "change": "21.79%",
      "isUp": true,
      "volume": "$1,870,425.00",
      "marketCap": "--",
      "holders": "8,346"
    },
    {
      "coinName": "NDB (NDB)",
      "address": "0xf8028b65005B0B45f76988d2A77910186E7af4eF",
      "price": "$0.0159",
      "change": "21.34%",
      "isUp": true,
      "volume": "$89,060.00",
      "marketCap": "--",
      "holders": "85"
    },
    {
      "coinName": "Graviton (GTON)",
      "address": "0x64d5baf5ac030e2b7c435add967f787ae94d0205",
      "price": "$1.2666",
      "change": "21.25%",
      "isUp": true,
      "volume": "$42,378.00",
      "marketCap": "$4,598,059.00",
      "holders": "713"
    },
    {
      "coinName": "Tokyo AU Token (TOKAU)",
      "address": "0xc409ec8a33f31437ed753c82eed3c5f16d6d7e22",
      "price": "$0.000.",
      "change": "17.50%",
      "isUp": true,
      "volume": "$129,219.00",
      "marketCap": "--",
      "holders": "78,190"
    },
    {
      "coinName": "OwlDAO token (OWL)",
      "address": "0x9085b4d52c3e0b8b6f9af6213e85a433c7d76f19",
      "price": "$0.0119",
      "change": "17.09%",
      "isUp": true,
      "volume": "$266.00",
      "marketCap": "--",
      "holders": "52,493"
    },
    {
      "coinName": "HPSv2 (HPS)",
      "address": "0xc9D53A339F3c22E016C6fA1E3Eb85AC32c75fED2",
      "price": "$0.2738",
      "change": "14.29%",
      "isUp": true,
      "volume": "$25,667.00",
      "marketCap": "--",
      "holders": "374"
    },
    {
      "coinName": "pTokens $ANRX ($ANRX)",
      "address": "0xe2e7329499e8ddb1f2b04ee4b35a8d7f6881e4ea",
      "price": "$0.0033",
      "change": "11.62%",
      "isUp": true,
      "volume": "$7,540.00",
      "marketCap": "$279,934.00",
      "holders": "4,373"
    },
    {
      "coinName": "cheesemaker.farm (CHS)",
      "address": "0xadd8a06fd58761a5047426e160b2b88ad3b9d464",
      "price": "$0.0087",
      "change": "11.06%",
      "isUp": true,
      "volume": "$8.00",
      "marketCap": "--",
      "holders": "5,916"
    },
    {
      "coinName": "Shard (SHARD)",
      "address": "0xd8a1734945b9ba38eb19a291b475e31f49e59877",
      "price": "$0.0350",
      "change": "10.95%",
      "isUp": true,
      "volume": "$474.00",
      "marketCap": "$1,075,188.00",
      "holders": "58,545"
    },
    {
      "coinName": "TORG (TORG)",
      "address": "0xcea59dce6a6d73a24e6d6944cfabc330814c098a",
      "price": "$0.000.",
      "change": "9.46%",
      "isUp": true,
      "volume": "$453.00",
      "marketCap": "--",
      "holders": "31,797"
    },
    {
      "coinName": "UniLend Finance Token (UFT)",
      "address": "0x2645d5f59d952ef2317c8e0aaa5a61c392ccd44d",
      "price": "$0.2570",
      "change": "9.44%",
      "isUp": true,
      "volume": "$13,279,503.00",
      "marketCap": "$16,020,527.00",
      "holders": "1,858"
    },
    {
      "coinName": "BSC Conflux (bCFX)",
      "address": "0x045c4324039dA91c52C55DF5D785385Aab073DcF",
      "price": "$0.0537",
      "change": "9.33%",
      "isUp": true,
      "volume": "$66,879,796.00",
      "marketCap": "$112,336,210.00",
      "holders": "10,392"
    },
    {
      "coinName": "Cake Monster (MONSTA)",
      "address": "0x8a5d7fcd4c90421d21d30fcc4435948ac3618b2f",
      "price": "$0.0012",
      "change": "8.93%",
      "isUp": true,
      "volume": "$16,961.00",
      "marketCap": "$7,488,339.00",
      "holders": "13,008"
    },
    {
      "coinName": "GamyFi (GFX)",
      "address": "0x65ad6a2288b2dd23e466226397c8f5d1794e58fc",
      "price": "$0.0571",
      "change": "7.41%",
      "isUp": true,
      "volume": "$7,661.00",
      "marketCap": "$182,627.00",
      "holders": "989"
    },
    {
      "coinName": "wazirx token (WRX)",
      "address": "0x8e17ed70334c87ece574c9d537bc153d8609e2a3",
      "price": "$0.2166",
      "change": "7.22%",
      "isUp": true,
      "volume": "$7,254,614.00",
      "marketCap": "$99,015,875.00",
      "holders": "8,227"
    },
    {
      "coinName": "SwftCoin (SWFTC)",
      "address": "0xe64e30276c2f826febd3784958d6da7b55dfbad3",
      "price": "$0.0017",
      "change": "6.61%",
      "isUp": true,
      "volume": "$3,747,816.00",
      "marketCap": "$10,824,442.00",
      "holders": "1,110"
    },
    {
      "coinName": "Ltradex (LTEX)",
      "address": "0xBcB3ac7a3ceB2d0C5E162A03901d6D7bb8602912",
      "price": "$0.000.",
      "change": "6.18%",
      "isUp": true,
      "volume": "$163,531.00",
      "marketCap": "--",
      "holders": "4,115"
    },
    {
      "coinName": "Binance-Peg Synthetix Network Token (SNX)",
      "address": "0x9ac983826058b8a9c7aa1c9171441191232e8404",
      "price": "$2.9308",
      "change": "5.79%",
      "isUp": true,
      "volume": "$78,134,062.00",
      "marketCap": "$684,978,265.00",
      "holders": "8,675"
    },
    {
      "coinName": "LIMOCOIN SWAP (LMCSWAP)",
      "address": "0x383094a91ef2767eed2b063ea40465670bf1c83f",
      "price": "$0.0064",
      "change": "5.34%",
      "isUp": true,
      "volume": "$14,161.00",
      "marketCap": "--",
      "holders": "98,105"
    },
    {
      "coinName": "Binance Beacon ETH (BETH)",
      "address": "0x250632378e573c6be1ac2f97fcdf00515d0aa91b",
      "price": "$1,511.",
      "change": "5.13%",
      "isUp": true,
      "volume": "$5,906,871.00",
      "marketCap": "--",
      "holders": "8,953"
    },
    {
      "coinName": "EarnX (EarnX)",
      "address": "0x0f76142D83ddEF359753ccA33647Cc4dCEe1C6d1",
      "price": "$0.0034",
      "change": "4.51%",
      "isUp": true,
      "volume": "$3,576.00",
      "marketCap": "--",
      "holders": "3,897"
    },
    {
      "coinName": "Binance-Peg Phala Network Token (PHA)",
      "address": "0x0112e557d400474717056c4e6d40edd846f38351",
      "price": "$0.0999",
      "change": "4.19%",
      "isUp": true,
      "volume": "$4,678,511.00",
      "marketCap": "$41,762,446.00",
      "holders": "8,663"
    },
    {
      "coinName": "GameStation (GAMER)",
      "address": "0x3f6b3595ecf70735d3f48d69b09c4e4506db3f47",
      "price": "$0.0065",
      "change": "4.11%",
      "isUp": true,
      "volume": "$1,128.00",
      "marketCap": "--",
      "holders": "460"
    },
    {
      "coinName": "NFTY Token (NFTY)",
      "address": "0x5774b2fc3e91af89f89141eacf76545e74265982",
      "price": "$0.0141",
      "change": "4.02%",
      "isUp": true,
      "volume": "$152,312.00",
      "marketCap": "$3,622,188.00",
      "holders": "13,222"
    },
    {
      "coinName": "WEB3 Inu (WEB3)",
      "address": "0xd0c4bc1b89bbd105eecb7eba3f13e7648c0de38f",
      "price": "$0.000.",
      "change": "4.01%",
      "isUp": true,
      "volume": "$1,042.00",
      "marketCap": "--",
      "holders": "340,128"
    },
    {
      "coinName": "COMMUNIQUE (CMQ)",
      "address": "0x074E91c178e4B4c6228357A5A0B6df5aD824f0d8",
      "price": "$0.0501",
      "change": "3.84%",
      "isUp": true,
      "volume": "$1,093,252.00",
      "marketCap": "--",
      "holders": "15,102"
    },
    {
      "coinName": "Binance-Peg Ethereum Classic (ETC)",
      "address": "0x3d6545b08693dae087e957cb1180ee38b9e3c25e",
      "price": "$38.501",
      "change": "3.65%",
      "isUp": true,
      "volume": "$2,798,641,066.00",
      "marketCap": "$5,270,434,537.00",
      "holders": "25,184"
    },
    {
      "coinName": "Jointer (JNTR)",
      "address": "0x5f2caa99fc378248ac02cbbaac27e3fa155ed2c4",
      "price": "$0.0205",
      "change": "3.55%",
      "isUp": true,
      "volume": "$44,532.00",
      "marketCap": "--",
      "holders": "5,280"
    },
    {
      "coinName": "Binance-Peg Kyber Network Crystal Token (KNC)",
      "address": "0xfe56d5892bdffc7bf58f2e84be1b2c32d21c308b",
      "price": "$1.990.",
      "change": "3.19%",
      "isUp": true,
      "volume": "$38,057,579.00",
      "marketCap": "$203,259,248.00",
      "holders": "4,009"
    },
    {
      "coinName": "Bat True Dollar (BTD)",
      "address": "0xd1102332a213e21faf78b69c03572031f3552c33",
      "price": "$0.0805",
      "change": "3.15%",
      "isUp": true,
      "volume": "$10,657.00",
      "marketCap": "--",
      "holders": "2,439"
    },
    {
      "coinName": "TETU Reward Token (TETU)",
      "address": "0x1f681b1c4065057e07b95a1e5e504fb2c85f4625",
      "price": "$0.0068",
      "change": "2.94%",
      "isUp": true,
      "volume": "$19,787.00",
      "marketCap": "$1,679,354.00",
      "holders": "30"
    },
    {
      "coinName": "Yearn Secure (YSEC)",
      "address": "0x56a0f16af7c8098141b363094fcf864d52831326",
      "price": "$0.1399",
      "change": "2.89%",
      "isUp": true,
      "volume": "$4,341.00",
      "marketCap": "$133,666.00",
      "holders": "39"
    },
    {
      "coinName": "Venus ETH (vETH)",
      "address": "0xf508fcd89b8bd15579dc79a6827cb4686a3592c8",
      "price": "$68.813",
      "change": "2.82%",
      "isUp": true,
      "volume": "$0.00",
      "marketCap": "$139,966,392.00",
      "holders": "7,846"
    },
    {
      "coinName": "ClinTex (CTI)",
      "address": "0x3f670f65b9ce89b82e82121fd68c340ac22c08d6",
      "price": "$0.0075",
      "change": "2.72%",
      "isUp": true,
      "volume": "$2,390,450.00",
      "marketCap": "$625,820.00",
      "holders": "629"
    },
    {
      "coinName": "QANX Token (QANX)",
      "address": "0xaaa7a10a8ee237ea61e8ac46c50a8db8bcc1baaa",
      "price": "$0.0107",
      "change": "2.57%",
      "isUp": true,
      "volume": "$133,086.00",
      "marketCap": "$23,314,070.00",
      "holders": "17,701"
    },
    {
      "coinName": "FEGtoken (FEG)",
      "address": "0xacfc95585d80ab62f67a14c566c1b7a49fe91167",
      "price": "$0.000.",
      "change": "2.45%",
      "isUp": true,
      "volume": "$574,885.00",
      "marketCap": "$14,371,726.00",
      "holders": "970,172"
    },
    {
      "coinName": "RFOX (RFOX)",
      "address": "0x0a3a21356793b49154fd3bbe91cbc2a16c0457f5",
      "price": "$0.0111",
      "change": "2.41%",
      "isUp": true,
      "volume": "$191,989.00",
      "marketCap": "$17,767,019.00",
      "holders": "13,274"
    },
    {
      "coinName": "loser coin (lowb)",
      "address": "0x843d4a358471547f51534e3e51fae91cb4dc3f28",
      "price": "$0.000.",
      "change": "2.32%",
      "isUp": true,
      "volume": "$376,025.00",
      "marketCap": "--",
      "holders": "141,433"
    },
    {
      "coinName": "CanYaCoin (CAN)",
      "address": "0x007ea5c0ea75a8df45d288a4debdd5bb633f9e56",
      "price": "$0.0096",
      "change": "2.14%",
      "isUp": true,
      "volume": "$0.00",
      "marketCap": "--",
      "holders": "987"
    },
    {
      "coinName": "Chess (CHESS)",
      "address": "0x20de22029ab63cf9a7cf5feb2b737ca1ee4c82a6",
      "price": "$0.2765",
      "change": "2.11%",
      "isUp": true,
      "volume": "$5,607,743.00",
      "marketCap": "$22,824,777.00",
      "holders": "16,307"
    },
    {
      "coinName": "BSCX (BSCX)",
      "address": "0x5ac52ee5b2a633895292ff6d8a89bb9190451587",
      "price": "$1.0902",
      "change": "2.01%",
      "isUp": true,
      "volume": "$0.00",
      "marketCap": "--",
      "holders": "15,842"
    }
  ]
}