{
  "data": [
    {
      "coinName": "FinNexus (FNX)",
      "address": "0xdfd9e2a17596cad6295ecffda42d9b6f63f7b5d5",
      "price": "$0.0076",
      "change": "72.24%",
      "isUp": true,
      "volume": "$184,825.00",
      "marketCap": "$2,711,791.00",
      "holders": "1,662"
    },
    {
      "coinName": "France REV Finance (FRF)",
      "address": "0x5a29c96fa93ffa8845fb7f8616a03aa85fcc11d6",
      "price": "$0.000.",
      "change": "63.02%",
      "isUp": true,
      "volume": "$7,657.00",
      "marketCap": "--",
      "holders": "2,000"
    },
    {
      "coinName": "Etermon (ETM)",
      "address": "0x75bded6bf44bb01527138673dcc064dbe3e7d96d",
      "price": "$0.0321",
      "change": "58.96%",
      "isUp": true,
      "volume": "$829,685.00",
      "marketCap": "--",
      "holders": "1,756"
    },
    {
      "coinName": "GourmetGalaxy (GUM)",
      "address": "0xc53708664b99df348dd27c3ac0759d2da9c40462",
      "price": "$0.4441",
      "change": "42.55%",
      "isUp": true,
      "volume": "$650,399.00",
      "marketCap": "$1,470,820.00",
      "holders": "7,578"
    },
    {
      "coinName": "Raven Protocol (RAVEN)",
      "address": "0xcd7c5025753a49f1881b31c48caa7c517bb46308",
      "price": "$0.0016",
      "change": "34.20%",
      "isUp": true,
      "volume": "$143,372.00",
      "marketCap": "$7,086,817.00",
      "holders": "3,294"
    },
    {
      "coinName": "ARIVA (ARV)",
      "address": "0x6679eb24f59dfe111864aec72b443d1da666b360",
      "price": "$0.0004",
      "change": "23.73%",
      "isUp": true,
      "volume": "$5,239,593.00",
      "marketCap": "$28,938,980.00",
      "holders": "201,650"
    },
    {
      "coinName": "Binance-Peg IoTeX Network (IOTX)",
      "address": "0x9678e42cebeb63f23197d726b29b1cb20d0064e5",
      "price": "$0.0930",
      "change": "23.44%",
      "isUp": true,
      "volume": "$255,175,177.00",
      "marketCap": "$887,519,638.00",
      "holders": "35,546"
    },
    {
      "coinName": "FlashX Ultra (FSXU)",
      "address": "0xa94b7a842aadb617a0b08fa744e033c6de2f7595",
      "price": "$0.0004",
      "change": "19.74%",
      "isUp": true,
      "volume": "$12.00",
      "marketCap": "$63,129.00",
      "holders": "3,524"
    },
    {
      "coinName": "Trust Wallet (TWT)",
      "address": "0x4b0f1812e5df2a09796481ff14017e6005508003",
      "price": "$1.1310",
      "change": "19.31%",
      "isUp": true,
      "volume": "$201,936,881.00",
      "marketCap": "$392,394,103.00",
      "holders": "269,479"
    },
    {
      "coinName": "Elemon Token (ELMON)",
      "address": "0xe3233fdb23f1c27ab37bd66a19a1f1762fcf5f3f",
      "price": "$0.2070",
      "change": "16.26%",
      "isUp": true,
      "volume": "$2,850,807.00",
      "marketCap": "--",
      "holders": "42,597"
    },
    {
      "coinName": "hoge.finance (HOGE)",
      "address": "0xa4fffc757e8c4f24e7b209c033c123d20983ad40",
      "price": "$0.0001",
      "change": "16.21%",
      "isUp": true,
      "volume": "$215,336.00",
      "marketCap": "$27,567,966.00",
      "holders": "15,642"
    },
    {
      "coinName": "THUGS (THUGS)",
      "address": "0xe10e9822a5de22f8761919310dda35cd997d63c0",
      "price": "$6.4329",
      "change": "14.25%",
      "isUp": true,
      "volume": "$0.00",
      "marketCap": "$4,286,409.00",
      "holders": "1,139"
    },
    {
      "coinName": "ParaSwap (PSP)",
      "address": "0xcafe001067cdef266afb7eb5a286dcfd277f3de5",
      "price": "$0.0873",
      "change": "13.41%",
      "isUp": true,
      "volume": "$1,531,051.00",
      "marketCap": "$34,971,494.00",
      "holders": "170"
    },
    {
      "coinName": "CafeSwap Token (BREW)",
      "address": "0x790be81c3ca0e53974be2688cdb954732c9862e1",
      "price": "$0.0202",
      "change": "12.56%",
      "isUp": true,
      "volume": "$4.00",
      "marketCap": "$245,826.00",
      "holders": "8,952"
    },
    {
      "coinName": "DAFI Token (DAFI)",
      "address": "0x22439be3aebc1590b05e3243780ed4156b629604",
      "price": "$0.0225",
      "change": "11.87%",
      "isUp": true,
      "volume": "$728,394.00",
      "marketCap": "$13,066,973.00",
      "holders": "277"
    },
    {
      "coinName": "Frontier Token (FRONT)",
      "address": "0x928e55dab735aa8260af3cedada18b5f70c72f1b",
      "price": "$0.5805",
      "change": "11.50%",
      "isUp": true,
      "volume": "$138,886,379.00",
      "marketCap": "$48,986,702.00",
      "holders": "11,236"
    },
    {
      "coinName": "Tokocrypto Token (TKO)",
      "address": "0x9f589e3eabe42ebc94a44727b3f3531c0c877809",
      "price": "$0.7310",
      "change": "11.46%",
      "isUp": true,
      "volume": "$28,595,507.00",
      "marketCap": "$55,027,777.00",
      "holders": "44,225"
    },
    {
      "coinName": "Binance-Peg Ethereum Classic (ETC)",
      "address": "0x3d6545b08693dae087e957cb1180ee38b9e3c25e",
      "price": "$43.375",
      "change": "11.37%",
      "isUp": true,
      "volume": "$2,425,527,717.00",
      "marketCap": "$5,799,948,883.00",
      "holders": "16,355"
    },
    {
      "coinName": "Binance-Peg Bitcoin Cash Token (BCH)",
      "address": "0x8ff795a6f4d97e7887c79bea79aba5cc76444adf",
      "price": "$370.88",
      "change": "11.09%",
      "isUp": true,
      "volume": "$4,232,968,639.00",
      "marketCap": "$7,052,524,485.00",
      "holders": "12,835"
    },
    {
      "coinName": "Venus BCH (vBCH)",
      "address": "0x5f0388ebc2b94fa8e123f404b79ccf5f40b29176",
      "price": "$7.4390",
      "change": "11.09%",
      "isUp": true,
      "volume": "$0.00",
      "marketCap": "$1,148,527.00",
      "holders": "576"
    },
    {
      "coinName": "Nemesis Wealth Projects BSC (NMS)",
      "address": "0x8cb4fdb148d87f7ec493e69391347bdd3ff1163f",
      "price": "$0.000.",
      "change": "10.53%",
      "isUp": true,
      "volume": "$614.00",
      "marketCap": "--",
      "holders": "1,075"
    },
    {
      "coinName": "ApeSwapFinance Banana (BANANA)",
      "address": "0x603c7f932ed1fc6575303d8fb018fdcbb0f39a95",
      "price": "$0.3826",
      "change": "10.52%",
      "isUp": true,
      "volume": "$2,172,227.00",
      "marketCap": "$40,429,087.00",
      "holders": "65,388"
    },
    {
      "coinName": "Binance-Peg Elrond Token (EGLD)",
      "address": "0xbf7c81fff98bbe61b40ed186e4afd6ddd01337fe",
      "price": "$185.95",
      "change": "10.31%",
      "isUp": true,
      "volume": "$350,632,268.00",
      "marketCap": "$4,031,499,065.00",
      "holders": "27,028"
    },
    {
      "coinName": "Binance-Peg EOS Token (EOS)",
      "address": "0x56b6fb708fc5732dec1afc8d8556423a2edccbd6",
      "price": "$2.4238",
      "change": "9.84%",
      "isUp": true,
      "volume": "$985,886,847.00",
      "marketCap": "$2,383,872,051.00",
      "holders": "29,581"
    },
    {
      "coinName": "WINk (WIN)",
      "address": "0xaef0d72a118ce24fee3cd1d43d383897d05b4e99",
      "price": "$0.0003",
      "change": "8.76%",
      "isUp": true,
      "volume": "$2,281,868.00",
      "marketCap": "--",
      "holders": "64,498"
    },
    {
      "coinName": "FLOKI (FLOKI)",
      "address": "0xfb5b838b6cfeedc2873ab27866079ac55363d37e",
      "price": "$0.000.",
      "change": "8.56%",
      "isUp": true,
      "volume": "$9,063,855.00",
      "marketCap": "$285,452,721.00",
      "holders": "342,018"
    },
    {
      "coinName": "Torum (XTM)",
      "address": "0xcd1faff6e578fa5cac469d2418c95671ba1a62fe",
      "price": "$0.1527",
      "change": "8.38%",
      "isUp": true,
      "volume": "$1,449,082.00",
      "marketCap": "$7,993,384.00",
      "holders": "12,072"
    },
    {
      "coinName": "VFOX (VFOX)",
      "address": "0x4d61577d8fd2208a0afb814ea089fdeae19ed202",
      "price": "$0.6776",
      "change": "7.50%",
      "isUp": true,
      "volume": "$7,234.00",
      "marketCap": "$14,225,316.00",
      "holders": "2,550"
    },
    {
      "coinName": "Easy V2 (EZ)",
      "address": "0x5512014efa6cd57764fa743756f7a6ce3358cc83",
      "price": "$2.130.",
      "change": "7.39%",
      "isUp": true,
      "volume": "$1,739,356.00",
      "marketCap": "--",
      "holders": "3,486"
    },
    {
      "coinName": "SafePal Token (SFP)",
      "address": "0xd41fdb03ba84762dd66a0af1a6c8540ff1ba5dfb",
      "price": "$0.8482",
      "change": "7.04%",
      "isUp": true,
      "volume": "$32,334,001.00",
      "marketCap": "$91,749,617.00",
      "holders": "128,558"
    },
    {
      "coinName": "Binance-Peg MANTRA DAO Token (OM)",
      "address": "0xf78d2e7936f5fe18308a3b2951a93b6c4a41f5e2",
      "price": "$0.0818",
      "change": "6.75%",
      "isUp": true,
      "volume": "$17,349,643.00",
      "marketCap": "$36,612,666.00",
      "holders": "1,914"
    },
    {
      "coinName": "Binance-Peg Celer Token (CELR)",
      "address": "0x1f9f6a696c6fd109cd3956f45dc709d2b3902163",
      "price": "$0.0436",
      "change": "6.69%",
      "isUp": true,
      "volume": "$47,456,534.00",
      "marketCap": "$245,926,046.00",
      "holders": "29,162"
    },
    {
      "coinName": "Binance-Peg Cardano Token (ADA)",
      "address": "0x3ee2200efb3400fabb9aacf31297cbdd1d435d47",
      "price": "$0.9566",
      "change": "6.66%",
      "isUp": true,
      "volume": "$1,557,534,408.00",
      "marketCap": "$32,251,763,251.00",
      "holders": "444,158"
    },
    {
      "coinName": "Venus ADA (vADA)",
      "address": "0x9a0af7fdb2065ce470d72664de73cae409da28ec",
      "price": "$0.0192",
      "change": "6.66%",
      "isUp": true,
      "volume": "$0.00",
      "marketCap": "--",
      "holders": "4,225"
    },
    {
      "coinName": "Venus Reward Token (VRT)",
      "address": "0x5f84ce30dc3cf7909101c69086c50de191895883",
      "price": "$0.0005",
      "change": "6.64%",
      "isUp": true,
      "volume": "$268,229.00",
      "marketCap": "$11,105,672.00",
      "holders": "43,559"
    },
    {
      "coinName": "RFOX (RFOX)",
      "address": "0x0a3a21356793b49154fd3bbe91cbc2a16c0457f5",
      "price": "$0.0498",
      "change": "6.45%",
      "isUp": true,
      "volume": "$819,129.00",
      "marketCap": "$72,712,331.00",
      "holders": "12,726"
    },
    {
      "coinName": "Venus DOT (vDOT)",
      "address": "0x1610bc33319e9398de5f57b33a5b184c806ad217",
      "price": "$0.4147",
      "change": "6.44%",
      "isUp": true,
      "volume": "$0.00",
      "marketCap": "$6,904,799.00",
      "holders": "4,644"
    },
    {
      "coinName": "808TA (808TA)",
      "address": "0xfd93917257b33c6d64dc24f7a60982589823e0cb",
      "price": "$0.000.",
      "change": "6.37%",
      "isUp": true,
      "volume": "$39.00",
      "marketCap": "--",
      "holders": "591"
    },
    {
      "coinName": "Binance-Peg Polkadot Token (DOT)",
      "address": "0x7083609fce4d1d8dc0c979aab8c869ea2c873402",
      "price": "$20.122",
      "change": "6.32%",
      "isUp": true,
      "volume": "$1,114,243,098.00",
      "marketCap": "$19,872,331,659.00",
      "holders": "164,925"
    },
    {
      "coinName": "Binance-Peg Litecoin Token (LTC)",
      "address": "0x4338665cbb7b2485a8855a139b75d5e34ab0db94",
      "price": "$122.27",
      "change": "6.20%",
      "isUp": true,
      "volume": "$887,164,035.00",
      "marketCap": "$8,534,331,192.00",
      "holders": "51,043"
    },
    {
      "coinName": "Billion Happiness (BHC)",
      "address": "0x6fd7c98458a943f469e1cf4ea85b173f5cd342f4",
      "price": "$43.212",
      "change": "6.18%",
      "isUp": true,
      "volume": "$170,447.00",
      "marketCap": "$2,160,636.00",
      "holders": "9,151"
    },
    {
      "coinName": "Venus LTC (vLTC)",
      "address": "0x57a5297f2cb2c0aac9d554660acd6d385ab50c6b",
      "price": "$2.4645",
      "change": "6.10%",
      "isUp": true,
      "volume": "$0.00",
      "marketCap": "$10,209,057.00",
      "holders": "1,381"
    },
    {
      "coinName": "Binance-Peg ELF Token (ELF)",
      "address": "0xa3f020a5c92e15be13caf0ee5c95cf79585eecc9",
      "price": "$0.3528",
      "change": "6.03%",
      "isUp": true,
      "volume": "$32,189,589.00",
      "marketCap": "$192,119,011.00",
      "holders": "883"
    },
    {
      "coinName": "SwftCoin (SWFTC)",
      "address": "0xe64e30276c2f826febd3784958d6da7b55dfbad3",
      "price": "$0.0022",
      "change": "5.80%",
      "isUp": true,
      "volume": "$3,106,180.00",
      "marketCap": "$14,362,095.00",
      "holders": "749"
    },
    {
      "coinName": "JulSwap (JulD)",
      "address": "0x5a41f637c3f7553dba6ddc2d3ca92641096577ea",
      "price": "$0.0183",
      "change": "5.75%",
      "isUp": true,
      "volume": "$463,132.00",
      "marketCap": "$10,821,040.00",
      "holders": "112,009"
    },
    {
      "coinName": "Venus SXP (vSXP)",
      "address": "0x2ff3d0f6990a40261c66e1ff2017acbc282eb6d0",
      "price": "$0.0309",
      "change": "5.52%",
      "isUp": true,
      "volume": "$0.00",
      "marketCap": "$12,239,477.00",
      "holders": "2,252"
    },
    {
      "coinName": "Graviton (GTON)",
      "address": "0x64d5baf5ac030e2b7c435add967f787ae94d0205",
      "price": "$1.6633",
      "change": "5.50%",
      "isUp": true,
      "volume": "$2,473.00",
      "marketCap": "$6,038,114.00",
      "holders": "716"
    },
    {
      "coinName": "Newscrypto (NWC)",
      "address": "0x968f6f898a6df937fc1859b323ac2f14643e3fed",
      "price": "$0.2450",
      "change": "5.47%",
      "isUp": true,
      "volume": "$2,870,384.00",
      "marketCap": "$36,506,159.00",
      "holders": "6,575"
    },
    {
      "coinName": "PizzaSwap (PIZZA)",
      "address": "0x2cc26dd730f548dc4ac291ae7d84a0c96980d2cb",
      "price": "$0.0531",
      "change": "5.43%",
      "isUp": true,
      "volume": "$33,575.00",
      "marketCap": "--",
      "holders": "4,017"
    },
    {
      "coinName": "Binance-Peg YFII.finance Token (YFII)",
      "address": "0x7f70642d88cf1c4a3a7abb072b53b929b653eda5",
      "price": "$2,189.",
      "change": "5.18%",
      "isUp": true,
      "volume": "$17,854,651.00",
      "marketCap": "$84,513,933.00",
      "holders": "1,477"
    }
  ]
}